mlogs/Adapt_history_logger_2.py
mlogs/__init__.py
mlogs/adapt_history_logger.py
mlogs/base_logger.py
mlogs/base_warp_logger.py
mlogs/flie_logger.py
mlogs/formaters.py
mlogs/mlogger.py
mlogs/stdout_logger.py
mlogs/utils.py
mlogs/third_party/notifiers/notifiers/__init__.py
mlogs/third_party/notifiers/notifiers/_version.py
mlogs/third_party/notifiers/notifiers/core.py
mlogs/third_party/notifiers/notifiers/exceptions.py
mlogs/third_party/notifiers/notifiers/logging.py
mlogs/third_party/notifiers/notifiers/providers/__init__.py
mlogs/third_party/notifiers/notifiers/providers/email.py
mlogs/third_party/notifiers/notifiers/providers/feishu.py
mlogs/third_party/notifiers/notifiers/providers/gitter.py
mlogs/third_party/notifiers/notifiers/providers/gmail.py
mlogs/third_party/notifiers/notifiers/providers/icloud.py
mlogs/third_party/notifiers/notifiers/providers/join.py
mlogs/third_party/notifiers/notifiers/providers/mailgun.py
mlogs/third_party/notifiers/notifiers/providers/pagerduty.py
mlogs/third_party/notifiers/notifiers/providers/popcornnotify.py
mlogs/third_party/notifiers/notifiers/providers/pushbullet.py
mlogs/third_party/notifiers/notifiers/providers/pushover.py
mlogs/third_party/notifiers/notifiers/providers/simplepush.py
mlogs/third_party/notifiers/notifiers/providers/slack.py
mlogs/third_party/notifiers/notifiers/providers/statuspage.py
mlogs/third_party/notifiers/notifiers/providers/telegram.py
mlogs/third_party/notifiers/notifiers/providers/twilio.py
mlogs/third_party/notifiers/notifiers/providers/victorops.py
mlogs/third_party/notifiers/notifiers/providers/zulip.py
mlogs/third_party/notifiers/notifiers/utils/__init__.py
mlogs/third_party/notifiers/notifiers/utils/helpers.py
mlogs/third_party/notifiers/notifiers/utils/requests.py
mlogs/third_party/notifiers/notifiers/utils/schema/__init__.py
mlogs/third_party/notifiers/notifiers/utils/schema/formats.py
mlogs/third_party/notifiers/notifiers/utils/schema/helpers.py
mlogs-0.3.5.dist-info/METADATA
mlogs-0.3.5.dist-info/WHEEL
mlogs-0.3.5.dist-info/top_level.txt
mlogs-0.3.5.dist-info/RECORD
