Metadata-Version: 2.1
Name: mlogs
Version: 0.3.5
Summary: loguru packaging log tools
Home-page: UNKNOWN
Author: Caturbhuja Das
Author-email: caturbhuja@foxmail.com
License: Apache 2.0
Platform: UNKNOWN
Classifier: Programming Language :: Python :: 3
Classifier: License :: OSI Approved :: MIT License
Classifier: Operating System :: OS Independent
Requires-Dist: loguru (>=0.6.0)
Requires-Dist: numpy (>=1.19.0)
Requires-Dist: jsonschema (>=4.0.0)
Requires-Dist: requests (>=2.27.1)
